{"ListVariables": [
{"Variable": "AvgSpeed" , "Values": [1.1236308501469026, 0]},
{"Variable": "CycleVariability" , "Values": [0.20274980392887504, 0]},
{"Variable": "DoubleStance" , "Values": [0.1934138614972154, 0]},
{"Variable": "MeanStepDuration" , "Values": [0.51, 0]},
{"Variable": "RoliTronc" , "Values": [0.15923853020417322, 0]},
{"Variable": "Smo_Ent_AccXWaist" , "Values": [0.25067030793696277, -1]},
{"Variable": "Smo_Ent_AccYWaist" , "Values": [0.2933670249274524, -1]},
{"Variable": "Smo_Ent_AccZWaist" , "Values": [0.212970802853853, -1]},
{"Variable": "Smo_Ent_GyrXWaist" , "Values": [0.35168293322663813, -1]},
{"Variable": "Smo_Ent_GyrYWaist" , "Values": [0.22204428278184202, -1]},
{"Variable": "Smo_Ent_GyrZWaist" , "Values": [0.21723426288151054, -1]},
{"Variable": "Smo_ROM_anML" , "Values": [10.542356411881824, -1]},
{"Variable": "Spr_SteT" , "Values": [0.51, -1]},
{"Variable": "Spr_SwT_L" , "Values": [0.4191666666666667, -1]},
{"Variable": "Spr_SwT_R" , "Values": [0.4215384615384616, -1]},
{"Variable": "Spr_UtrT" , "Values": [1.02, -1]},
{"Variable": "Sta_Att_aAP" , "Values": [25.918788860233843, -1]},
{"Variable": "Sta_Att_aML" , "Values": [16.511170270140184, -1]},
{"Variable": "Sta_Att_gAP" , "Values": [33.40210626260425, -1]},
{"Variable": "Sta_Att_gCC" , "Values": [37.106901629915775, -1]},
{"Variable": "Sta_Att_gML" , "Values": [7.54150835548264, -1]},
{"Variable": "Sta_Lyap_AccXWaist" , "Values": [0.13765395381772977, -1]},
{"Variable": "Sta_Lyap_AccYWaist" , "Values": [0.12848751296555144, -1]},
{"Variable": "Sta_Lyap_AccZWaist" , "Values": [0.15030337450107514, -1]},
{"Variable": "Sta_Lyap_GyrXWaist" , "Values": [0.13675435326432514, -1]},
{"Variable": "Sta_Lyap_GyrYWaist" , "Values": [0.09950534985738654, -1]},
{"Variable": "Sta_Lyap_GyrZWaist" , "Values": [0.09725793267772165, -1]},
{"Variable": "Sta_RMS_aML_LB" , "Values": [0.12769909851559674, -1]},
{"Variable": "Sta_RMS_gAP_LB" , "Values": [13.617419391142587, -1]},
{"Variable": "Sta_ROM_lML" , "Values": [1.1606967216844404, -1]},
{"Variable": "Ste_FFTqaAP_LB" , "Values": [0.46247880661039903, 1]},
{"Variable": "Ste_FFTqaCC_LB" , "Values": [0.45986872811076623, 1]},
{"Variable": "Ste_FFTqaML_LB" , "Values": [0.44741976533041244, 1]},
{"Variable": "Ste_FFTqgAP_LB" , "Values": [0.49162612182438603, 1]},
{"Variable": "Ste_FFTqgCC_LB" , "Values": [0.43749108580270385, 1]},
{"Variable": "Ste_FFTqgML_LB" , "Values": [0.34440118322289953, 1]},
{"Variable": "Ste_P2_aAP_LB2" , "Values": [0.6888166525188728, 1]},
{"Variable": "Ste_P2_aCC_LB2" , "Values": [0.7102788808496472, 1]},
{"Variable": "Ste_cvSwT_L" , "Values": [0.0299533184360226, -1]},
{"Variable": "Ste_cvSwT_R" , "Values": [0.03585197573793522, -1]},
{"Variable": "Ste_cvT" , "Values": [0.058692664890571546, -1]},
{"Variable": "Stu_L" , "Values": [1.0952357542311095, 1]},
{"Variable": "Stu_RMS_aAPF" , "Values": [0.9080294795448771, 1]},
{"Variable": "Stu_RMS_aCCF" , "Values": [1.0726397187799517, 1]},
{"Variable": "Stu_turnN" , "Values": [1, -1]},
{"Variable": "SwingMeanStrideDuration" , "Values": [0.02670087547027296, 0]},
{"Variable": "Sym_HRaAP_LB" , "Values": [3.312792383063932, 1]},
{"Variable": "Sym_HRaCC_LB" , "Values": [4.234203721715859, 1]},
{"Variable": "Sym_P1P2_aAP_LB2" , "Values": [1.0462135911889827, 1]},
{"Variable": "Sym_P1P2_aCC_LB2" , "Values": [1.0374789858580769, 1]},
{"Variable": "Syn_dsT" , "Values": [0.1934138614972154, -1]},
{"Variable": "Syn_ffT" , "Values": [1.0, -1]}
]
}