{"ListVariables": [
{"Variable": "AvgSpeed" , "Values": [0.8124382916488471, 0]},
{"Variable": "CycleVariability" , "Values": [0.21849737531075722, 0]},
{"Variable": "DoubleStance" , "Values": [0.2548509720741523, 0]},
{"Variable": "MeanStepDuration" , "Values": [0.6573684210526316, 0]},
{"Variable": "RoliTronc" , "Values": [0.08380115303296722, 0]},
{"Variable": "Smo_Ent_AccXWaist" , "Values": [0.2823734246763322, -1]},
{"Variable": "Smo_Ent_AccYWaist" , "Values": [0.31677203172172275, -1]},
{"Variable": "Smo_Ent_AccZWaist" , "Values": [0.27763773613777887, -1]},
{"Variable": "Smo_Ent_GyrXWaist" , "Values": [0.3936760895508928, -1]},
{"Variable": "Smo_Ent_GyrYWaist" , "Values": [0.24269031756916126, -1]},
{"Variable": "Smo_Ent_GyrZWaist" , "Values": [0.21888544573116947, -1]},
{"Variable": "Smo_ROM_anML" , "Values": [15.023526484020751, -1]},
{"Variable": "Spr_SteT" , "Values": [0.6573684210526316, -1]},
{"Variable": "Spr_SwT_L" , "Values": [0.4770588235294118, -1]},
{"Variable": "Spr_SwT_R" , "Values": [0.47789473684210526, -1]},
{"Variable": "Spr_UtrT" , "Values": [1.52, -1]},
{"Variable": "Sta_Att_aAP" , "Values": [-73.02487450527184, -1]},
{"Variable": "Sta_Att_aML" , "Values": [-22.603466195545984, -1]},
{"Variable": "Sta_Att_gAP" , "Values": [52.09187689838197, -1]},
{"Variable": "Sta_Att_gCC" , "Values": [37.59704566080565, -1]},
{"Variable": "Sta_Att_gML" , "Values": [27.862127843019845, -1]},
{"Variable": "Sta_Lyap_AccXWaist" , "Values": [0.1151597226019482, -1]},
{"Variable": "Sta_Lyap_AccYWaist" , "Values": [0.12549753710922115, -1]},
{"Variable": "Sta_Lyap_AccZWaist" , "Values": [0.16258830565868723, -1]},
{"Variable": "Sta_Lyap_GyrXWaist" , "Values": [0.04797414286107036, -1]},
{"Variable": "Sta_Lyap_GyrYWaist" , "Values": [0.14370600727040184, -1]},
{"Variable": "Sta_Lyap_GyrZWaist" , "Values": [0.14054953057332742, -1]},
{"Variable": "Sta_RMS_aML_LB" , "Values": [0.06366665502316432, -1]},
{"Variable": "Sta_RMS_gAP_LB" , "Values": [10.938968243607524, -1]},
{"Variable": "Sta_ROM_lML" , "Values": [0.8166718656521869, -1]},
{"Variable": "Ste_FFTqaAP_LB" , "Values": [0.4875546614976197, 1]},
{"Variable": "Ste_FFTqaCC_LB" , "Values": [0.48066576555891816, 1]},
{"Variable": "Ste_FFTqaML_LB" , "Values": [0.3929295663770773, 1]},
{"Variable": "Ste_FFTqgAP_LB" , "Values": [0.49816815641541445, 1]},
{"Variable": "Ste_FFTqgCC_LB" , "Values": [0.4195715609865514, 1]},
{"Variable": "Ste_FFTqgML_LB" , "Values": [0.43904352381242995, 1]},
{"Variable": "Ste_P2_aAP_LB2" , "Values": [0.8560071022632568, 1]},
{"Variable": "Ste_P2_aCC_LB2" , "Values": [0.7119887525383788, 1]},
{"Variable": "Ste_cvSwT_L" , "Values": [0.054644931704464474, -1]},
{"Variable": "Ste_cvSwT_R" , "Values": [0.05015549575654494, -1]},
{"Variable": "Ste_cvT" , "Values": [0.2655701769638614, -1]},
{"Variable": "Stu_L" , "Values": [0.6470445316032176, 1]},
{"Variable": "Stu_RMS_aAPF" , "Values": [1.0494110515353887, 1]},
{"Variable": "Stu_RMS_aCCF" , "Values": [1.0252520587594047, 1]},
{"Variable": "Stu_turnN" , "Values": [1, -1]},
{"Variable": "SwingMeanStrideDuration" , "Values": [0.0025450420504245248, 0]},
{"Variable": "Sym_HRaAP_LB" , "Values": [2.0358118197983046, 1]},
{"Variable": "Sym_HRaCC_LB" , "Values": [2.638533392276562, 1]},
{"Variable": "Sym_P1P2_aAP_LB2" , "Values": [0.9579292606809118, 1]},
{"Variable": "Sym_P1P2_aCC_LB2" , "Values": [1.0187625518506538, 1]},
{"Variable": "Syn_dsT" , "Values": [0.2548509720741523, -1]},
{"Variable": "Syn_ffT" , "Values": [0.0, -1]}
]
}