{"ListVariables": [
{"Variable": "AvgSpeed" , "Values": [0.8756674108570576, 0]},
{"Variable": "CycleVariability" , "Values": [0.2183887338056944, 0]},
{"Variable": "DoubleStance" , "Values": [0.2625985415648176, 0]},
{"Variable": "MeanStepDuration" , "Values": [0.5918749999999999, 0]},
{"Variable": "RoliTronc" , "Values": [0.2990709085201445, 0]},
{"Variable": "Smo_Ent_AccXWaist" , "Values": [0.20647812570281665, -1]},
{"Variable": "Smo_Ent_AccYWaist" , "Values": [0.41579285380132347, -1]},
{"Variable": "Smo_Ent_AccZWaist" , "Values": [0.18960919984459682, -1]},
{"Variable": "Smo_Ent_GyrXWaist" , "Values": [0.4757809851908455, -1]},
{"Variable": "Smo_Ent_GyrYWaist" , "Values": [0.25324239160637907, -1]},
{"Variable": "Smo_Ent_GyrZWaist" , "Values": [0.2803948224838516, -1]},
{"Variable": "Smo_ROM_anML" , "Values": [13.302379420156633, -1]},
{"Variable": "Spr_SteT" , "Values": [0.5918749999999999, -1]},
{"Variable": "Spr_SwT_L" , "Values": [0.45866666666666667, -1]},
{"Variable": "Spr_SwT_R" , "Values": [0.446, -1]},
{"Variable": "Spr_UtrT" , "Values": [2.18, -1]},
{"Variable": "Sta_Att_aAP" , "Values": [-116.97066686722354, -1]},
{"Variable": "Sta_Att_aML" , "Values": [26.891913955022584, -1]},
{"Variable": "Sta_Att_gAP" , "Values": [50.2587082159215, -1]},
{"Variable": "Sta_Att_gCC" , "Values": [67.13031498018309, -1]},
{"Variable": "Sta_Att_gML" , "Values": [50.20118898529178, -1]},
{"Variable": "Sta_Lyap_AccXWaist" , "Values": [0.14673556306731014, -1]},
{"Variable": "Sta_Lyap_AccYWaist" , "Values": [0.15181563859161357, -1]},
{"Variable": "Sta_Lyap_AccZWaist" , "Values": [0.15798851091993615, -1]},
{"Variable": "Sta_Lyap_GyrXWaist" , "Values": [0.14433015560545476, -1]},
{"Variable": "Sta_Lyap_GyrYWaist" , "Values": [0.12024116376103952, -1]},
{"Variable": "Sta_Lyap_GyrZWaist" , "Values": [0.1785230050925679, -1]},
{"Variable": "Sta_RMS_aML_LB" , "Values": [0.11996367773239147, -1]},
{"Variable": "Sta_RMS_gAP_LB" , "Values": [10.715441067006559, -1]},
{"Variable": "Sta_ROM_lML" , "Values": [0.2123146628210821, -1]},
{"Variable": "Ste_FFTqaAP_LB" , "Values": [0.42085930233077773, 1]},
{"Variable": "Ste_FFTqaCC_LB" , "Values": [0.4705086974438354, 1]},
{"Variable": "Ste_FFTqaML_LB" , "Values": [0.4425262583606938, 1]},
{"Variable": "Ste_FFTqgAP_LB" , "Values": [0.48027689815661073, 1]},
{"Variable": "Ste_FFTqgCC_LB" , "Values": [0.46750576495508045, 1]},
{"Variable": "Ste_FFTqgML_LB" , "Values": [0.3272178344081965, 1]},
{"Variable": "Ste_P2_aAP_LB2" , "Values": [0.6955899052621332, 1]},
{"Variable": "Ste_P2_aCC_LB2" , "Values": [0.7098778720789475, 1]},
{"Variable": "Ste_cvSwT_L" , "Values": [0.0336506886709018, -1]},
{"Variable": "Ste_cvSwT_R" , "Values": [0.03909326406762938, -1]},
{"Variable": "Ste_cvT" , "Values": [0.04169395358479323, -1]},
{"Variable": "Stu_L" , "Values": [0.7444639981138871, 1]},
{"Variable": "Stu_RMS_aAPF" , "Values": [0.9980140210018953, 1]},
{"Variable": "Stu_RMS_aCCF" , "Values": [0.8260064517019777, 1]},
{"Variable": "Stu_turnN" , "Values": [1, -1]},
{"Variable": "SwingMeanStrideDuration" , "Values": [0.025353590985530833, 0]},
{"Variable": "Sym_HRaAP_LB" , "Values": [2.1254327512550315, 1]},
{"Variable": "Sym_HRaCC_LB" , "Values": [2.643707773490078, 1]},
{"Variable": "Sym_P1P2_aAP_LB2" , "Values": [0.9327673712585196, 1]},
{"Variable": "Sym_P1P2_aCC_LB2" , "Values": [0.9449624232176397, 1]},
{"Variable": "Syn_dsT" , "Values": [0.2625985415648176, -1]},
{"Variable": "Syn_ffT" , "Values": [1.2631578947368436, -1]}
]
}